apstrim/__init__.py
apstrim/__main__.py
apstrim/apstrim.py
apstrim/cad_pvaccess.py
apstrim/helpTxtView.py
apstrim/liteCNS.py
apstrim/pubEPICS.py
apstrim/scan.py
apstrim/view.py
apstrim-4.2.3.dist-info/METADATA
apstrim-4.2.3.dist-info/WHEEL
apstrim-4.2.3.dist-info/licenses/LICENSE
apstrim-4.2.3.dist-info/RECORD
