Metadata-Version: 2.4
Name: apstrim
Version: 4.2.3
Summary: Logger and extractor of time-series data (e.g. EPICS PVs or liteServer LDOs).
Project-URL: Homepage, https://github.com/ASukhanov/apstrim
Project-URL: Bug Tracker, https://github.com/ASukhanov/apstrim/issues
Author-email: Andrei Sukhanov <cyxandr@gmail.com>
License-File: LICENSE
Classifier: License :: OSI Approved :: MIT License
Classifier: Operating System :: OS Independent
Classifier: Programming Language :: Python :: 3
Requires-Python: >=3.7
Requires-Dist: caproto
Requires-Dist: liteaccess
Requires-Dist: msgpack
